CHANGES.rst
MANIFEST.in
README.rst
setup.py
Products/__init__.py
Products.ContentWellPortlets.egg-info/PKG-INFO
Products.ContentWellPortlets.egg-info/SOURCES.txt
Products.ContentWellPortlets.egg-info/dependency_links.txt
Products.ContentWellPortlets.egg-info/entry_points.txt
Products.ContentWellPortlets.egg-info/namespace_packages.txt
Products.ContentWellPortlets.egg-info/not-zip-safe
Products.ContentWellPortlets.egg-info/requires.txt
Products.ContentWellPortlets.egg-info/top_level.txt
Products/ContentWellPortlets/__init__.py
Products/ContentWellPortlets/configure.zcml
Products/ContentWellPortlets/upgrades.zcml
Products/ContentWellPortlets/browser/__init__.py
Products/ContentWellPortlets/browser/configure.zcml
Products/ContentWellPortlets/browser/interfaces.py
Products/ContentWellPortlets/browser/manager.py
Products/ContentWellPortlets/browser/viewlets.py
Products/ContentWellPortlets/browser/styles/ContentWellPortlets.css
Products/ContentWellPortlets/browser/templates/manage-content-type.pt
Products/ContentWellPortlets/browser/templates/manage-contextual.pt
Products/ContentWellPortlets/browser/templates/managefooterportlets.pt
Products/ContentWellPortlets/browser/templates/manageinheaderportlets.pt
Products/ContentWellPortlets/browser/templates/manageportletsabove.pt
Products/ContentWellPortlets/browser/templates/manageportletsbelow.pt
Products/ContentWellPortlets/browser/templates/manageportletsbelowtitle.pt
Products/ContentWellPortlets/browser/templates/portletmanager.pt
Products/ContentWellPortlets/browser/templates/renderer.pt
Products/ContentWellPortlets/locales/contentwellportlets.pot
Products/ContentWellPortlets/locales/rebuild_i18n.sh
Products/ContentWellPortlets/locales/es/LC_MESSAGES/contentwellportlets.mo
Products/ContentWellPortlets/locales/es/LC_MESSAGES/contentwellportlets.po
Products/ContentWellPortlets/locales/fr/LC_MESSAGES/contentwellportlets.mo
Products/ContentWellPortlets/locales/fr/LC_MESSAGES/contentwellportlets.po
Products/ContentWellPortlets/locales/it/LC_MESSAGES/contentwellportlets.mo
Products/ContentWellPortlets/locales/it/LC_MESSAGES/contentwellportlets.po
Products/ContentWellPortlets/profiles/default/browserlayer.xml
Products/ContentWellPortlets/profiles/default/cssregistry.xml
Products/ContentWellPortlets/profiles/default/metadata.xml
Products/ContentWellPortlets/profiles/default/portlets.xml
Products/ContentWellPortlets/profiles/default/viewlets.xml
