Metadata-Version: 2.1
Name: Products.ContentWellPortlets
Version: 4.3.1
Summary: A Plone product that enables you to add portlets to the central column in a page
Home-page: http://weblion.psu.edu
Author: WebLion
Author-email: support@weblion.psu.edu
License: GPL
Keywords: plone portletmanager
Platform: UNKNOWN
Classifier: Development Status :: 5 - Production/Stable
Classifier: Framework :: Plone
Classifier: License :: OSI Approved :: GNU General Public License v2 or later (GPLv2+)
Classifier: Programming Language :: Python
Classifier: Topic :: Software Development :: Libraries :: Python Modules
Provides-Extra: test
